skaha/__init__.py
skaha/client.py
skaha/context.py
skaha/images.py
skaha/models.py
skaha/overview.py
skaha/session.py
skaha/hooks/__init__.py
skaha/hooks/httpx/__init__.py
skaha/hooks/httpx/errors.py
skaha/utils/build.py
skaha/utils/convert.py
skaha/utils/logs.py
skaha-1.7.0.dist-info/licenses/LICENSE
skaha-1.7.0.dist-info/METADATA
skaha-1.7.0.dist-info/WHEEL
skaha-1.7.0.dist-info/top_level.txt
skaha-1.7.0.dist-info/RECORD
