Metadata-Version: 2.4
Name: skaha
Version: 1.7.0
Summary: Python Client for CANFAR Science Platform
Author-email: Shiny Brar <shiny.brar@nrc-cnrc.gc.ca>
License:                     GNU AFFERO GENERAL PUBLIC LICENSE
Project-URL: homepage, https://shinybrar.github.io/skaha/
Project-URL: repository, https://github.com/shinybrar/skaha
Project-URL: documentation, https://shinybrar.github.io/skaha/
Project-URL: changelog, https://shinybrar.github.io/skaha/changelog/
Project-URL: issues, https://github.com/shinybrar/skaha/issues
Keywords: skaha,canfar,python,client,container,platform
Classifier: Development Status :: 4 - Beta
Classifier: Environment :: Console
Classifier: Intended Audience :: Developers
Classifier: Intended Audience :: Education
Classifier: Intended Audience :: Science/Research
Classifier: Intended Audience :: System Administrators
Classifier: Natural Language :: English
Classifier: Operating System :: MacOS :: MacOS X
Classifier: Operating System :: POSIX :: Linux
Classifier: Programming Language :: Python :: 3 :: Only
Classifier: Programming Language :: Python :: 3.9
Classifier: Programming Language :: Python :: 3.10
Classifier: Programming Language :: Python :: 3.11
Classifier: Programming Language :: Python :: 3.12
Classifier: Programming Language :: Python :: 3.13
Classifier: Programming Language :: Python :: Implementation :: CPython
Classifier: Topic :: Scientific/Engineering :: Astronomy
Classifier: Topic :: Scientific/Engineering :: Physics
Classifier: Topic :: Software Development :: Libraries :: Python Modules
Classifier: License :: OSI Approved :: GNU Affero General Public License v3 or later (AGPLv3+)
Requires-Python: >=3.9
License-File: LICENSE
Requires-Dist: defusedxml>=0.7.1
Requires-Dist: httpx>=0.28.1
Requires-Dist: pydantic>=2.9.2
Requires-Dist: rich>=13.9.4
Requires-Dist: toml>=0.10.2
Requires-Dist: typer>=0.16.0
Requires-Dist: vos>=3.6.1.1
Dynamic: license-file
